SpoutGL/Spout.dll
SpoutGL/__init__.py
SpoutGL/_spoutgl.cp38-win_amd64.pyd
SpoutGL/enums.py
SpoutGL/helpers.py
spoutgl-0.1.1.dist-info/LICENSE
spoutgl-0.1.1.dist-info/METADATA
spoutgl-0.1.1.dist-info/WHEEL
spoutgl-0.1.1.dist-info/top_level.txt
spoutgl-0.1.1.dist-info/RECORD
