Metadata-Version: 2.4
Name: SpoutGL
Version: 0.1.1
Summary: Wrapper around Spout frame streaming library for Windows
Home-page: https://github.com/jlai/Python-SpoutGL
Author: Jason Lai
License: BSD-3-Clause
Classifier: Development Status :: 3 - Alpha
Classifier: Operating System :: Microsoft :: Windows
Classifier: License :: OSI Approved :: BSD License
Classifier: Topic :: Multimedia :: Graphics :: Capture
Classifier: Topic :: Multimedia :: Graphics :: Viewers
Requires-Python: >=3.8
License-File: LICENSE
Provides-Extra: test
Dynamic: author
Dynamic: classifier
Dynamic: description
Dynamic: description-content-type
Dynamic: home-page
Dynamic: license
Dynamic: license-file
Dynamic: provides-extra
Dynamic: requires-python
Dynamic: summary
